ceffyl/Ceffyl.py
ceffyl/Sampler.py
ceffyl/__init__.py
ceffyl/ceffyl_gp.py
ceffyl/chain_utils.py
ceffyl/densities.py
ceffyl/metrics.py
ceffyl/models.py
ceffyl-1.41.2.dist-info/licenses/LICENSE
ceffyl-1.41.2.dist-info/METADATA
ceffyl-1.41.2.dist-info/WHEEL
ceffyl-1.41.2.dist-info/top_level.txt
ceffyl-1.41.2.dist-info/RECORD
