Metadata-Version: 2.4
Name: ceffyl
Version: 1.41.2
Summary: Software to rapidly and flexibly analyse Pulsar Timing Array data via factorised likelihood methods (Lamb et al. 2023)
Author-email: "William G. Lamb" <william.g.lamb@vanderbilt.edu>
License-File: LICENSE
Requires-Dist: encor>=1.1.5
Requires-Dist: enterprise-pulsar<4.0.0,>=3.4.4
Requires-Dist: enterprise_extensions<4.0.0,>=3.0.2
Requires-Dist: h5py<4.0.0,>=3.11.0
Requires-Dist: kalepy<2.0.0,>=1.4
Requires-Dist: KDEpy<2.0.0,>=1.1.0
Requires-Dist: la_forge<2.0.0,>=1.1.0
Requires-Dist: natsort<9.0.0,>=8.4.0
Requires-Dist: numpy<3.0.0,>=1.23.5
Requires-Dist: PTMCMCSampler<3.0.0,>=2.1.2
Provides-Extra: gp
Requires-Dist: holodeck-gw<2.0.0,>=1.0.0; extra == "gp"
Dynamic: license-file
